wagtail_localize_panel/__init__.py
wagtail_localize_panel/apps.py
wagtail_localize_panel/config.py
wagtail_localize_panel/migrations/0001_add_permission.py
wagtail_localize_panel/migrations/0002_add_permission.py
wagtail_localize_panel/migrations/__init__.py
wagtail_localize_panel/models.py
wagtail_localize_panel/notify_translations.py
wagtail_localize_panel/templates/wagtail_localize_panel/home/workflow_pages_to_translate.html
wagtail_localize_panel/utils.py
wagtail_localize_panel/views.py
wagtail_localize_panel/wagtail_hooks.py
wagtail_localize_panel-0.2.1.dist-info/LICENSE
wagtail_localize_panel-0.2.1.dist-info/WHEEL
wagtail_localize_panel-0.2.1.dist-info/METADATA
wagtail_localize_panel-0.2.1.dist-info/RECORD
